{"pole_angles": 0.0, "episode_reward": 0.6334370139968896, "episode_lengths": 4.665629860031104, "training_iteration_time_ms": 1.564, "grad_wait_time_ms": 1.564, "apply_grad_time_ms": 0.0, "apply_grad_throughput": 0.0, "synch_weights_time_ms": 1.301, "num_env_steps_sampled": 5780, "num_env_steps_trained": 5780, "num_agent_steps_sampled": 5780, "num_agent_steps_trained": 5780, "_timestamp": 1666875545.556656, "_runtime": 50.91641092300415, "_step": 2, "pls work1": {"_type": "image-file", "sha256": "dd0c0f309f26a5940acc2be53cde2cc01230b178dc59835ad375756bc55c3f28", "size": 81, "path": "media/images/pls work1_2_dd0c0f309f26a5940acc.png", "format": "png", "width": 4, "height": 4, "caption": "Top: Output, Bottom: Input"}, "_wandb": {"runtime": 51}}